momentum_cli/__init__.py
momentum_cli/cli.py
momentum_cli/test_runner.py
momentum_cli-0.0.3.dist-info/METADATA
momentum_cli-0.0.3.dist-info/WHEEL
momentum_cli-0.0.3.dist-info/entry_points.txt
momentum_cli-0.0.3.dist-info/RECORD
